driveutil/__init__.py
driveutil-0.2.1.dist-info/LICENSE
driveutil-0.2.1.dist-info/METADATA
driveutil-0.2.1.dist-info/WHEEL
driveutil-0.2.1.dist-info/top_level.txt
driveutil-0.2.1.dist-info/RECORD
