Metadata-Version: 2.1
Name: driveutil
Version: 0.2.1
Summary: A Small Package Made By Yeeterboi4 For Drive Uses! (Windows Only...)
Home-page: https://github.com/Yeeterboi4/driveutil
Author: Yeeterboi4
Author-email: not-yet@gmail.com
License: UNKNOWN
Keywords: drive,usb,util
Platform: UNKNOWN
Classifier: Development Status :: 3 - Alpha
Classifier: Intended Audience :: Developers
Classifier: Operating System :: OS Independent
Classifier: License :: OSI Approved :: MIT License
Classifier: Programming Language :: Python :: 3
Classifier: Programming Language :: Python :: 3.5
Classifier: Programming Language :: Python :: 3.6
Classifier: Programming Language :: Python :: 3.7
Classifier: Programming Language :: Python :: 3.8
Classifier: Programming Language :: Python :: 3.9
License-File: LICENSE
